calculadora/__init__.py
calculadora/operacoes.py
calculadora_liblivia-0.1.0.dist-info/METADATA
calculadora_liblivia-0.1.0.dist-info/WHEEL
calculadora_liblivia-0.1.0.dist-info/top_level.txt
calculadora_liblivia-0.1.0.dist-info/RECORD
