Metadata-Version: 2.4
Name: calculadora_liblivia
Version: 0.1.0
Summary: Uma biblioteca simples de operações matemáticas.
Author: Livia
Classifier: Programming Language :: Python :: 3
Classifier: License :: OSI Approved :: MIT License
Requires-Python: >=3.6
Dynamic: author
Dynamic: classifier
Dynamic: requires-python
Dynamic: summary
